my_own_package/__init__.py
Horia_s_first_package-0.1.0.dist-info/METADATA
Horia_s_first_package-0.1.0.dist-info/WHEEL
Horia_s_first_package-0.1.0.dist-info/top_level.txt
Horia_s_first_package-0.1.0.dist-info/RECORD
