Metadata-Version: 2.1
Name: Horia-s-first-package
Version: 0.1.0
Summary: My first package - Horia
Author: Litan Horia
Author-email: horialitan@yahoo.com
